{
    "type":  "zip",
    "version":  "2.3.1",
    "description":  "Readable source code documentation for 20 programming languages.",
    "homepage":  "https://www.naturaldocs.org/",
    "license":  "AGPL-3.0-only",
    "dependencies":  [

                     ],
    "url":  "https://www.naturaldocs.org/download/natural_docs/2.3.1/Natural_Docs_2.3.1.zip",
    "hash":  "92144e2deb1ff2606d29343cfea203ea890549ad2f77c03df1cea2d8014972cb",
    "installer":  {
                      "args":  [

                               ]
                  },
    "bin":  "NaturalDocs.exe",
    "autoupdate":  {
                       "url":  "https://www.naturaldocs.org/download/natural_docs/$version/Natural_Docs_$version.zip"
                   }
}
