{
    "type":  "zip",
    "version":  "0.5.11",
    "description":  "Simplistic interactive filtering tool",
    "homepage":  "https://github.com/peco/peco/",
    "license":  "MIT",
    "dependencies":  [

                     ],
    "url":  "https://github.com/peco/peco/releases/download/v0.5.11/peco_windows_amd64.zip",
    "hash":  "bd0f92cf415f43b9fe19515d8c49b31683826cf3626b485217e6487d3635c95d",
    "installer":  {
                      "args":  [

                               ]
                  },
    "bin":  "peco.exe",
    "autoupdate":  {
                       "url":  "https://github.com/peco/peco/releases/download/v$version/peco_windows_amd64.zip"
                   }
}
