{
    "type":  "zip",
    "version":  "1.6.13",
    "description":  "Quick, simple but powerful image editor (Community Edition)",
    "homepage":  "https://photoflare.io",
    "license":  "GPL-3.0-or-later",
    "dependencies":  [

                     ],
    "url":  "https://launchpad.net/photofiltre-lx/trunk/v1.6.13/%2Bdownload/Photoflare_CE_1.6.13_amd64_win_portable.zip",
    "hash":  "md5:291b64c8725b48738aea51a065c88db1",
    "installer":  {
                      "args":  [

                               ]
                  },
    "bin":  "ce_photoflare.exe",
    "autoupdate":  {
                       "url":  "https://launchpad.net/photofiltre-lx/trunk/v$version/%2Bdownload/Photoflare_CE_$matchHead_amd64_win_portable.zip"
                   }
}
